scikit_surgeryvideoutils-0.1.0.dist-info/DESCRIPTION.rst
scikit_surgeryvideoutils-0.1.0.dist-info/METADATA
scikit_surgeryvideoutils-0.1.0.dist-info/RECORD
scikit_surgeryvideoutils-0.1.0.dist-info/WHEEL
scikit_surgeryvideoutils-0.1.0.dist-info/entry_points.txt
scikit_surgeryvideoutils-0.1.0.dist-info/metadata.json
scikit_surgeryvideoutils-0.1.0.dist-info/top_level.txt
sksurgeryvideoutils/__init__.py
sksurgeryvideoutils/_version.py
sksurgeryvideoutils/ui/__init__.py
sksurgeryvideoutils/ui/sksurgerycharucotest_command_line.py
sksurgeryvideoutils/ui/sksurgerycharucotest_demo.py
sksurgeryvideoutils/ui/sksurgeryvideolag_command_line.py
sksurgeryvideoutils/ui/sksurgeryvideolag_demo.py
sksurgeryvideoutils/utils/__init__.py
sksurgeryvideoutils/utils/image_utils.py
