Metadata-Version: 2.0
Name: scikit-surgeryvideoutils
Version: 0.1.0
Summary: scikit-surgeryvideoutils
Home-page: https://weisslab.cs.ucl.ac.uk/WEISS/SoftwareRepositories/SNAPPY/scikit-surgeryvideoutils
Author: Matt Clarkson
Author-email: m.clarkson@ucl.ac.uk
License: BSD-3 license
Keywords: medical imaging
Platform: UNKNOWN
Classifier: Development Status :: 3 - Alpha
Classifier: Intended Audience :: Developers
Classifier: Intended Audience :: Healthcare Industry
Classifier: Intended Audience :: Information Technology
Classifier: Intended Audience :: Science/Research
Classifier: License :: OSI Approved :: BSD License
Classifier: Programming Language :: Python
Classifier: Programming Language :: Python :: 2
Classifier: Programming Language :: Python :: 3
Classifier: Topic :: Scientific/Engineering :: Information Analysis
Classifier: Topic :: Scientific/Engineering :: Medical Science Apps.
Requires-Dist: PySide2 (>=5.12.0)
Requires-Dist: numpy (>=1.11)
Requires-Dist: opencv-contrib-python (>=3.4.4)
Requires-Dist: scikit-surgeryimage (>=0.1.1)
Requires-Dist: six (>=1.10)
